nb_hideinputs/__init__.py
nb_hideinputs-0.2.0.dist-info/entry_points.txt
nb_hideinputs-0.2.0.dist-info/LICENSE
nb_hideinputs-0.2.0.dist-info/WHEEL
nb_hideinputs-0.2.0.dist-info/METADATA
nb_hideinputs-0.2.0.dist-info/RECORD
